dbtrolls/__main__.py
dbtrolls/__init__.py
dbtrolls-1.3.dist-info/DESCRIPTION.rst
dbtrolls-1.3.dist-info/WHEEL
dbtrolls-1.3.dist-info/top_level.txt
dbtrolls-1.3.dist-info/entry_points.txt
dbtrolls-1.3.dist-info/zip-safe
dbtrolls-1.3.dist-info/RECORD
dbtrolls-1.3.dist-info/metadata.json
dbtrolls-1.3.dist-info/METADATA
