Metadata-Version: 2.0
Name: dbtrolls
Version: 1.3
Summary: dbtrolls - A simple tool to make Dev's life happy.
Home-page: https://github.com/caputomarcos/dbtrolls
Author: Marcos Caputo
Author-email: caputo.marcos@gmail.com
License: GPL
Platform: UNKNOWN
Classifier: Development Status :: 4 - Beta
Classifier: Intended Audience :: Developers
Classifier: Topic :: Utilities
Classifier: License :: OSI Approved :: GNU General Public License (GPL)
Classifier: Programming Language :: Python :: 3
Requires-Dist: pyyaml
Provides-Extra: dev
Requires-Dist: pyyaml; extra == 'dev'
Requires-Dist: mock (==2.0.0); extra == 'dev'
